setup.py
punj_distributions/Binomialdistribution.py
punj_distributions/Gaussiandistribution.py
punj_distributions/Generaldistribution.py
punj_distributions/__init__.py
punj_distributions.egg-info/PKG-INFO
punj_distributions.egg-info/SOURCES.txt
punj_distributions.egg-info/dependency_links.txt
punj_distributions.egg-info/not-zip-safe
punj_distributions.egg-info/top_level.txt