Metadata-Version: 1.0
Name: punj-distributions
Version: 0.3
Summary: Gaussian & Binomial distributions
Home-page: UNKNOWN
Author: UNKNOWN
Author-email: UNKNOWN
License: UNKNOWN
Platform: UNKNOWN
